pygments_periwinkle_lexer/__init__.py
pygments_periwinkle_lexer/periwinkle_lexer.py
pygments_periwinkle_lexer-0.0.11.dist-info/LICENSE
pygments_periwinkle_lexer-0.0.11.dist-info/METADATA
pygments_periwinkle_lexer-0.0.11.dist-info/WHEEL
pygments_periwinkle_lexer-0.0.11.dist-info/entry_points.txt
pygments_periwinkle_lexer-0.0.11.dist-info/top_level.txt
pygments_periwinkle_lexer-0.0.11.dist-info/RECORD
