Metadata-Version: 2.1
Name: pygments-periwinkle-lexer
Version: 0.0.11
Summary: Лексер для Барвінку.
Home-page: https://github.com/periwinkle-lang
Author: Федуняк Роман
Author-email: fedynuak.roma@gmail.com
License: MIT License
Classifier: License :: OSI Approved :: MIT License
Classifier: Natural Language :: Ukrainian
Classifier: Programming Language :: Python :: 3 :: Only
Classifier: Environment :: Plugins
License-File: LICENSE
Requires-Dist: Pygments >=2.14.0
